nickpyhw/__init__.py
nickpyhw/lib2.py
nickpyhw/setup.py
nickpyhw-0.1.dist-info/METADATA
nickpyhw-0.1.dist-info/WHEEL
nickpyhw-0.1.dist-info/top_level.txt
nickpyhw-0.1.dist-info/RECORD
