Metadata-Version: 2.1
Name: nickpyhw
Version: 0.1
Summary: Taiwan No. 1
Home-page: http://github.com/storborg/nickpyhw
Author: NICK Hsieh
Author-email: f226609234@gmail.com
License: MIT
Platform: UNKNOWN
